LICENSE
MANIFEST.in
README.rst
setup.py
bee_django_referral/__init__.py
bee_django_referral/admin.py
bee_django_referral/apps.py
bee_django_referral/decorators.py
bee_django_referral/exports.py
bee_django_referral/forms.py
bee_django_referral/models.py
bee_django_referral/moderation.py
bee_django_referral/qr.py
bee_django_referral/signals.py
bee_django_referral/tests.py
bee_django_referral/urls.py
bee_django_referral/utils.py
bee_django_referral/validators.py
bee_django_referral/views.py
bee_django_referral.egg-info/PKG-INFO
bee_django_referral.egg-info/SOURCES.txt
bee_django_referral.egg-info/dependency_links.txt
bee_django_referral.egg-info/top_level.txt
bee_django_referral/migrations/0001_initial.py
bee_django_referral/migrations/0001_initial.pyc
bee_django_referral/migrations/0002_usershareimage_timestamp.py
bee_django_referral/migrations/0002_usershareimage_timestamp.pyc
bee_django_referral/migrations/0003_auto_20180514_1812.py
bee_django_referral/migrations/0003_auto_20180514_1812.pyc
bee_django_referral/migrations/0004_auto_20180515_1557.py
bee_django_referral/migrations/0004_auto_20180515_1557.pyc
bee_django_referral/migrations/0005_auto_20180706_1545.py
bee_django_referral/migrations/0005_auto_20180706_1545.pyc
bee_django_referral/migrations/0006_auto_20180706_1552.py
bee_django_referral/migrations/0006_auto_20180706_1552.pyc
bee_django_referral/migrations/0007_auto_20180706_1614.py
bee_django_referral/migrations/0007_auto_20180706_1614.pyc
bee_django_referral/migrations/0008_auto_20180706_1627.py
bee_django_referral/migrations/0008_auto_20180706_1627.pyc
bee_django_referral/migrations/0009_auto_20180706_1630.py
bee_django_referral/migrations/0009_auto_20180706_1630.pyc
bee_django_referral/migrations/0010_auto_20180708_1350.py
bee_django_referral/migrations/0010_auto_20180708_1350.pyc
bee_django_referral/migrations/0011_activity_link.py
bee_django_referral/migrations/0011_activity_link.pyc
bee_django_referral/migrations/0012_auto_20190821_1315.py
bee_django_referral/migrations/0012_auto_20190821_1315.pyc
bee_django_referral/migrations/0013_auto_20190826_1626.py
bee_django_referral/migrations/0013_auto_20190826_1626.pyc
