Metadata-Version: 1.1
Name: bee-django-referral
Version: 0.1.24
Summary: A simple Django app to conduct Web-based referral.
Home-page: http://www.example.com/
Author: zhangyue
Author-email: zhangyue@zhenpuedu.com
License: MIT License
Platform: UNKNOWN
Classifier: Environment :: Web Environment
Classifier: Framework :: Django
Classifier: Intended Audience :: Developers
Classifier: License :: OSI Approved :: MIT License
Classifier: Operating System :: OS Independent
Classifier: Programming Language :: Python
Classifier: Programming Language :: Python :: 2
Classifier: Programming Language :: Python :: 2.7
Classifier: Topic :: Internet :: WWW/HTTP
Classifier: Topic :: Internet :: WWW/HTTP :: Dynamic Content
